imxIcons/__init__.py
imxIcons/iconEntity.py
imxIcons/iconService.py
imxIcons/iconServiceModels.py
imxIcons/py.typed
imxIcons/domain/__init__.py
imxIcons/domain/default_icons.py
imxIcons/domain/helpers.py
imxIcons/domain/icon_library.py
imxIcons/domain/supportedIconTypes.py
imxIcons/domain/supportedImxVersions.py
imxIcons/domain/svg_data.py
imxIcons/domain/atbvvInstallation/__init__.py
imxIcons/domain/atbvvInstallation/atbvvBeacon_v124.py
imxIcons/domain/atbvvInstallation/atbvvBeacon_v500.py
imxIcons/domain/axleCounterDetection/__init__.py
imxIcons/domain/axleCounterDetection/axleCounterDetectionPoint_v124.py
imxIcons/domain/axleCounterDetection/axleCounterDetectionPoint_v500.py
imxIcons/domain/departureSignal/__init__.py
imxIcons/domain/departureSignal/departureSignal_imx500.py
imxIcons/domain/insulatedJoint/__init__.py
imxIcons/domain/insulatedJoint/insulatedJoint_v124.py
imxIcons/domain/insulatedJoint/insulatedJoint_v500.py
imxIcons/domain/levelCrossing/__init__.py
imxIcons/domain/levelCrossing/levelCrossing_v124.py
imxIcons/domain/levelCrossing/levelCrossing_v500.py
imxIcons/domain/reflectorPost/__init__.py
imxIcons/domain/reflectorPost/reflector_post_v124.py
imxIcons/domain/reflectorPost/reflector_post_v500.py
imxIcons/domain/sign/__init__.py
imxIcons/domain/sign/sign_imx124.py
imxIcons/domain/sign/sign_imx500.py
imxIcons/domain/sign/speedsign_imx124.py
imxIcons/domain/sign/speedsign_imx500.py
imxIcons/domain/signal/__init__.py
imxIcons/domain/signal/illuminated_signal_v124.py
imxIcons/domain/signal/illuminated_signal_v500.py
imxIcons/domain/signal/signal_imx124.py
imxIcons/domain/signal/signal_imx500.py
imxicons-0.2.9.dist-info/METADATA
imxicons-0.2.9.dist-info/WHEEL
imxicons-0.2.9.dist-info/licenses/LICENSE
imxicons-0.2.9.dist-info/RECORD
