Metadata-Version: 2.4
Name: imxIcons
Version: 0.2.9
Summary: python imx insights module to get information from imx files
Project-URL: Documentation, https://open-imx.github.io/imxIcons/
Project-URL: Source, https://github.com/open-imx/ImxIcons
Author-email: Hzd <Hazedd@users.noreply.github.com>, Open-Imx <open-imx@organisation.noreply.github.com>
License-File: LICENSE
Classifier: Development Status :: 4 - Beta
Classifier: Intended Audience :: Developers
Classifier: License :: OSI Approved :: GNU General Public License v3 or later (GPLv3+)
Classifier: Programming Language :: Python :: 3.10
Classifier: Programming Language :: Python :: 3.11
Classifier: Programming Language :: Python :: 3.12
Classifier: Programming Language :: Python :: 3.13
Requires-Python: >=3.10
Requires-Dist: lxml
Requires-Dist: pydantic
Requires-Dist: types-lxml
